shazbot/__init__.py
shazbot/_nbdev.py
shazbot/blocks_utils.py
shazbot/chunkadelic.py
shazbot/core.py
shazbot/data.py
shazbot/train_audio_algebra.py
shazbot/viz.py
shazbot-0.0.1.dist-info/LICENSE
shazbot-0.0.1.dist-info/METADATA
shazbot-0.0.1.dist-info/WHEEL
shazbot-0.0.1.dist-info/entry_points.txt
shazbot-0.0.1.dist-info/top_level.txt
shazbot-0.0.1.dist-info/RECORD
